{
  "id": "official-qz-inventions-inventeurs",
  "name_fr": "Inventions & Inventeurs",
  "name_en": "Inventions & Inventors",
  "description_fr": "Qui a inventé quoi ? Du téléphone à l'ampoule, des frères Lumière à Nikola Tesla.",
  "description_en": "Who invented what? From the telephone to the lightbulb, from the Lumière brothers to Nikola Tesla.",
  "category": "inventions",
  "difficulty": "mix",
  "locale_primary": "international",
  "question_count": 15,
  "questions": [
    {
      "position": 1,
      "type": "multiple_choice",
      "question_fr": "Qui a inventé le téléphone ?",
      "question_en": "Who invented the telephone?",
      "answers_fr": ["Thomas Edison", "Alexander Graham Bell", "Nikola Tesla", "Antonio Meucci"],
      "answers_en": ["Thomas Edison", "Alexander Graham Bell", "Nikola Tesla", "Antonio Meucci"],
      "correct_answer_index": 1,
      "explanation_fr": "Bell a déposé le brevet en 1876, mais Antonio Meucci a démontré le concept dès 1860.",
      "explanation_en": "Bell filed the patent in 1876, but Antonio Meucci demonstrated the concept as early as 1860.",
      "difficulty": "easy",
      "media": null
    },
    {
      "position": 2,
      "type": "multiple_choice",
      "question_fr": "Qui a inventé l'ampoule électrique commercialisée ?",
      "question_en": "Who invented the commercial light bulb?",
      "answers_fr": ["Volta", "Edison", "Tesla", "Faraday"],
      "answers_en": ["Volta", "Edison", "Tesla", "Faraday"],
      "correct_answer_index": 1,
      "explanation_fr": "Thomas Edison a perfectionné et commercialisé l'ampoule en 1879. Joseph Swan en a fait une similaire la même année.",
      "explanation_en": "Thomas Edison perfected and commercialized the bulb in 1879. Joseph Swan made a similar one the same year.",
      "difficulty": "easy",
      "media": null
    },
    {
      "position": 3,
      "type": "true_false",
      "question_fr": "Les frères Lumière ont inventé le cinéma.",
      "question_en": "The Lumière brothers invented cinema.",
      "correct_answer": true,
      "explanation_fr": "Auguste et Louis Lumière ont organisé la première projection publique payante en décembre 1895 à Paris.",
      "explanation_en": "Auguste and Louis Lumière organized the first paying public screening in December 1895 in Paris.",
      "difficulty": "easy",
      "media": null
    },
    {
      "position": 4,
      "type": "multiple_choice",
      "question_fr": "Qui a découvert la radioactivité avec son mari ?",
      "question_en": "Who discovered radioactivity with her husband?",
      "answers_fr": ["Lise Meitner", "Marie Curie", "Rosalind Franklin", "Hedy Lamarr"],
      "answers_en": ["Lise Meitner", "Marie Curie", "Rosalind Franklin", "Hedy Lamarr"],
      "correct_answer_index": 1,
      "explanation_fr": "Marie Curie et Pierre Curie ont étudié la radioactivité, prix Nobel de physique en 1903.",
      "explanation_en": "Marie Curie and Pierre Curie studied radioactivity, Nobel Prize in Physics in 1903.",
      "difficulty": "easy",
      "media": null
    },
    {
      "position": 5,
      "type": "multiple_choice",
      "question_fr": "Qui a inventé l'imprimerie à caractères mobiles en Europe ?",
      "question_en": "Who invented the movable type printing press in Europe?",
      "answers_fr": ["Léonard de Vinci", "Gutenberg", "Galilée", "Newton"],
      "answers_en": ["Leonardo da Vinci", "Gutenberg", "Galileo", "Newton"],
      "correct_answer_index": 1,
      "explanation_fr": "Johannes Gutenberg a perfectionné l'imprimerie à caractères mobiles vers 1450 à Mayence.",
      "explanation_en": "Johannes Gutenberg perfected movable type printing around 1450 in Mainz.",
      "difficulty": "medium",
      "media": null
    },
    {
      "position": 6,
      "type": "fill_blank",
      "question_fr": "L'inventeur du World Wide Web (le web) s'appelle Tim ___.",
      "question_en": "The inventor of the World Wide Web is named Tim ___.",
      "correct_answer_fr": "berners-lee",
      "correct_answer_en": "berners-lee",
      "alternatives_fr": ["berners-lee", "berners lee", "bernerslee"],
      "alternatives_en": ["berners-lee", "berners lee", "bernerslee"],
      "explanation_fr": "Tim Berners-Lee a inventé le web au CERN en 1989.",
      "explanation_en": "Tim Berners-Lee invented the web at CERN in 1989.",
      "difficulty": "medium",
      "media": null
    },
    {
      "position": 7,
      "type": "multiple_choice",
      "question_fr": "Qui a inventé la pile électrique ?",
      "question_en": "Who invented the electric battery?",
      "answers_fr": ["Galvani", "Volta", "Ampère", "Faraday"],
      "answers_en": ["Galvani", "Volta", "Ampère", "Faraday"],
      "correct_answer_index": 1,
      "explanation_fr": "Alessandro Volta invente la pile en 1800. L'unité 'volt' porte son nom.",
      "explanation_en": "Alessandro Volta invented the battery in 1800. The unit 'volt' is named after him.",
      "difficulty": "medium",
      "media": null
    },
    {
      "position": 8,
      "type": "true_false",
      "question_fr": "Albert Einstein a inventé la bombe atomique.",
      "question_en": "Albert Einstein invented the atomic bomb.",
      "correct_answer": false,
      "explanation_fr": "Faux. Einstein a découvert E=mc². La bombe a été développée par le projet Manhattan dirigé par Oppenheimer.",
      "explanation_en": "False. Einstein discovered E=mc². The bomb was developed by the Manhattan Project led by Oppenheimer.",
      "difficulty": "medium",
      "media": null
    },
    {
      "position": 9,
      "type": "multiple_choice",
      "question_fr": "Qui a inventé l'avion ?",
      "question_en": "Who invented the airplane?",
      "answers_fr": ["Otto Lilienthal", "Frères Wright", "Clément Ader", "Louis Blériot"],
      "answers_en": ["Otto Lilienthal", "Wright Brothers", "Clément Ader", "Louis Blériot"],
      "correct_answer_index": 1,
      "explanation_fr": "Les frères Wright ont effectué le premier vol motorisé contrôlé le 17 décembre 1903.",
      "explanation_en": "The Wright brothers made the first controlled powered flight on December 17, 1903.",
      "difficulty": "easy",
      "media": null
    },
    {
      "position": 10,
      "type": "multiple_choice",
      "question_fr": "Qui a découvert la pénicilline ?",
      "question_en": "Who discovered penicillin?",
      "answers_fr": ["Pasteur", "Fleming", "Koch", "Lister"],
      "answers_en": ["Pasteur", "Fleming", "Koch", "Lister"],
      "correct_answer_index": 1,
      "explanation_fr": "Alexander Fleming a découvert la pénicilline par accident en 1928.",
      "explanation_en": "Alexander Fleming discovered penicillin by accident in 1928.",
      "difficulty": "easy",
      "media": null
    },
    {
      "position": 11,
      "type": "fill_blank",
      "question_fr": "Le frigorigène inventé par Carl von ___ a permis le développement du réfrigérateur moderne.",
      "question_en": "The refrigerant invented by Carl von ___ enabled modern refrigeration.",
      "correct_answer_fr": "linde",
      "correct_answer_en": "linde",
      "alternatives_fr": ["linde"],
      "alternatives_en": ["linde"],
      "explanation_fr": "Carl von Linde a développé un système de réfrigération à compression dans les années 1870.",
      "explanation_en": "Carl von Linde developed a compression refrigeration system in the 1870s.",
      "difficulty": "hard",
      "media": null
    },
    {
      "position": 12,
      "type": "true_false",
      "question_fr": "Steve Jobs et Steve Wozniak ont fondé Apple en 1976.",
      "question_en": "Steve Jobs and Steve Wozniak founded Apple in 1976.",
      "correct_answer": true,
      "explanation_fr": "Apple a été fondée le 1er avril 1976 par Steve Jobs, Steve Wozniak et Ronald Wayne.",
      "explanation_en": "Apple was founded on April 1, 1976 by Steve Jobs, Steve Wozniak, and Ronald Wayne.",
      "difficulty": "easy",
      "media": null
    },
    {
      "position": 13,
      "type": "multiple_choice",
      "question_fr": "Qui a inventé la dynamite ?",
      "question_en": "Who invented dynamite?",
      "answers_fr": ["Curie", "Nobel", "Mendeleïev", "Becquerel"],
      "answers_en": ["Curie", "Nobel", "Mendeleev", "Becquerel"],
      "correct_answer_index": 1,
      "explanation_fr": "Alfred Nobel a inventé la dynamite en 1867. Il a légué sa fortune pour les prix Nobel.",
      "explanation_en": "Alfred Nobel invented dynamite in 1867. He left his fortune to fund the Nobel Prizes.",
      "difficulty": "medium",
      "media": null
    },
    {
      "position": 14,
      "type": "multiple_choice",
      "question_fr": "Qui a réalisé la première greffe cardiaque humaine ?",
      "question_en": "Who performed the first human heart transplant?",
      "answers_fr": ["Alexis Carrel", "Christiaan Barnard", "Norman Shumway", "Denton Cooley"],
      "answers_en": ["Alexis Carrel", "Christiaan Barnard", "Norman Shumway", "Denton Cooley"],
      "correct_answer_index": 1,
      "explanation_fr": "Christiaan Barnard a réalisé la première greffe cardiaque humaine en 1967 au Cap.",
      "explanation_en": "Christiaan Barnard performed the first human heart transplant in 1967 in Cape Town.",
      "difficulty": "hard",
      "media": null
    },
    {
      "position": 15,
      "type": "fill_blank",
      "question_fr": "L'inventeur de la vaccination contre la rage et de la pasteurisation s'appelle Louis ___.",
      "question_en": "The inventor of rabies vaccination and pasteurization is named Louis ___.",
      "correct_answer_fr": "pasteur",
      "correct_answer_en": "pasteur",
      "alternatives_fr": ["pasteur"],
      "alternatives_en": ["pasteur"],
      "explanation_fr": "Louis Pasteur a aussi prouvé le rôle des microbes dans les maladies.",
      "explanation_en": "Louis Pasteur also proved the role of microbes in diseases.",
      "difficulty": "easy",
      "media": null
    }
  ]
}
